tap_wonolo/__init__.py
tap_wonolo/client.py
tap_wonolo/version.py
tap_wonolo/schemas/job_requests.json
tap_wonolo/schemas/jobs.json
tap_wonolo/schemas/users.json
tap_wonolo-0.1.2.dist-info/LICENSE
tap_wonolo-0.1.2.dist-info/METADATA
tap_wonolo-0.1.2.dist-info/WHEEL
tap_wonolo-0.1.2.dist-info/entry_points.txt
tap_wonolo-0.1.2.dist-info/top_level.txt
tap_wonolo-0.1.2.dist-info/RECORD
