Metadata-Version: 2.1
Name: tap-wonolo
Version: 0.1.2
Summary: Singer.io tap for extracting data from Wonolo REST API
Home-page: https://github.com/goodeggs/tap-wonolo
Author: David Wallace
Author-email: david.wallace@goodeggs.com
License: GPLv3
Keywords: singer tap python wonolo
Platform: UNKNOWN
Classifier: License :: OSI Approved :: GNU General Public License v3 (GPLv3)
Classifier: Natural Language :: English
Classifier: Topic :: Software Development
Classifier: Intended Audience :: Developers
Classifier: Operating System :: OS Independent
Classifier: Development Status :: 5 - Production/Stable
Classifier: Programming Language :: Python :: 3 :: Only
Classifier: Programming Language :: Python :: 3.6
Classifier: Programming Language :: Python :: 3.7
Classifier: Programming Language :: Python :: 3.8
Requires-Python: >=3.6
Requires-Dist: requests (>=2.22.0)
Requires-Dist: attrs (>=19.3.0)
Requires-Dist: singer-python (==5.8.1)
Requires-Dist: backoff (==1.8.0)
Requires-Dist: rollbar (>=0.14.7)
